pytonapi/__init__.py
pytonapi/exceptions.py
pytonapi/utils.py
pytonapi/async_tonapi/__init__.py
pytonapi/async_tonapi/client.py
pytonapi/async_tonapi/methods/__init__.py
pytonapi/async_tonapi/methods/accounts.py
pytonapi/async_tonapi/methods/blockchain.py
pytonapi/async_tonapi/methods/dns.py
pytonapi/async_tonapi/methods/events.py
pytonapi/async_tonapi/methods/jettons.py
pytonapi/async_tonapi/methods/nft.py
pytonapi/async_tonapi/methods/rates.py
pytonapi/async_tonapi/methods/staking.py
pytonapi/async_tonapi/methods/storage.py
pytonapi/async_tonapi/methods/traces.py
pytonapi/schema/__init__.py
pytonapi/schema/_address.py
pytonapi/schema/_balance.py
pytonapi/schema/accounts.py
pytonapi/schema/blockchain.py
pytonapi/schema/dns.py
pytonapi/schema/domains.py
pytonapi/schema/events.py
pytonapi/schema/jettons.py
pytonapi/schema/nft.py
pytonapi/schema/rates.py
pytonapi/schema/staking.py
pytonapi/schema/storage.py
pytonapi/schema/traces.py
pytonapi/tonapi/__init__.py
pytonapi/tonapi/client.py
pytonapi/tonapi/methods/__init__.py
pytonapi/tonapi/methods/accounts.py
pytonapi/tonapi/methods/blockchain.py
pytonapi/tonapi/methods/dns.py
pytonapi/tonapi/methods/events.py
pytonapi/tonapi/methods/jettons.py
pytonapi/tonapi/methods/nft.py
pytonapi/tonapi/methods/rates.py
pytonapi/tonapi/methods/staking.py
pytonapi/tonapi/methods/storage.py
pytonapi/tonapi/methods/traces.py
pytonapi_oz-0.0.1.dist-info/LICENSE
pytonapi_oz-0.0.1.dist-info/METADATA
pytonapi_oz-0.0.1.dist-info/WHEEL
pytonapi_oz-0.0.1.dist-info/top_level.txt
pytonapi_oz-0.0.1.dist-info/RECORD
